odoo/addons/mrp_subcontracting_lot_number_propagation/README.rst
odoo/addons/mrp_subcontracting_lot_number_propagation/__init__.py
odoo/addons/mrp_subcontracting_lot_number_propagation/__manifest__.py
odoo/addons/mrp_subcontracting_lot_number_propagation/i18n/it.po
odoo/addons/mrp_subcontracting_lot_number_propagation/i18n/mrp_subcontracting_lot_number_propagation.pot
odoo/addons/mrp_subcontracting_lot_number_propagation/models/__init__.py
odoo/addons/mrp_subcontracting_lot_number_propagation/models/mrp_bom.py
odoo/addons/mrp_subcontracting_lot_number_propagation/models/mrp_production.py
odoo/addons/mrp_subcontracting_lot_number_propagation/models/stock_move.py
odoo/addons/mrp_subcontracting_lot_number_propagation/models/stock_move_line.py
odoo/addons/mrp_subcontracting_lot_number_propagation/readme/CONTRIBUTORS.rst
odoo/addons/mrp_subcontracting_lot_number_propagation/readme/DESCRIPTION.rst
odoo/addons/mrp_subcontracting_lot_number_propagation/static/description/icon.png
odoo/addons/mrp_subcontracting_lot_number_propagation/static/description/index.html
odoo/addons/mrp_subcontracting_lot_number_propagation/tests/__init__.py
odoo/addons/mrp_subcontracting_lot_number_propagation/tests/test_mrp_subcontracting.py
odoo/addons/mrp_subcontracting_lot_number_propagation/views/stock_move_line.xml
odoo_addon_mrp_subcontracting_lot_number_propagation-15.0.0.1.0.5.dist-info/METADATA
odoo_addon_mrp_subcontracting_lot_number_propagation-15.0.0.1.0.5.dist-info/WHEEL
odoo_addon_mrp_subcontracting_lot_number_propagation-15.0.0.1.0.5.dist-info/top_level.txt
odoo_addon_mrp_subcontracting_lot_number_propagation-15.0.0.1.0.5.dist-info/RECORD
