Metadata-Version: 2.1
Name: odoo-addon-mrp-subcontracting-lot-number-propagation
Version: 15.0.0.1.0.5
Summary: Propagate a serial number from a component to a finished product (subcontracting integration)
Home-page: https://github.com/OCA/manufacture
Author: Camptocamp, Odoo Community Association (OCA)
Author-email: support@odoo-community.org
License: AGPL-3
Platform: UNKNOWN
Classifier: Programming Language :: Python
Classifier: Framework :: Odoo
Classifier: Framework :: Odoo :: 15.0
Classifier: License :: OSI Approved :: GNU Affero General Public License v3
Classifier: Development Status :: 4 - Beta
Requires-Python: >=3.8
Requires-Dist: odoo-addon-mrp-lot-number-propagation <15.1dev,>=15.0dev
Requires-Dist: odoo <15.1dev,>=15.0a
